Cit/__init__.py
Cit/basic.py
Cit/cit_url.py
Cit/cit_wget.py
Cit/main.py
Cit/test.py
Cit/test01.py
Cit/test02.py
cit-0.4.2.dist-info/entry_points.txt
cit-0.4.2.dist-info/WHEEL
cit-0.4.2.dist-info/METADATA
cit-0.4.2.dist-info/RECORD
