Metadata-Version: 2.1
Name: cit
Version: 0.4.2
Summary: 让github的下载速度比之前快一千倍
Home-page: https://github.com/solider245/cit.git
License: MIT
Keywords: git,github,github加速
Author: 中箭的吴起
Author-email: solider245@gmail.com
Requires-Python: >=3.8,<4.0
Classifier: License :: OSI Approved :: MIT License
Classifier: Programming Language :: Python :: 3
Classifier: Programming Language :: Python :: 3.8
Classifier: Programming Language :: Python :: 3.9
Classifier: Topic :: Software Development :: Build Tools
Classifier: Topic :: Software Development :: Libraries :: Python Modules
Requires-Dist: python-string-utils (>=1.0.0,<2.0.0)
Requires-Dist: requests (>=2.25.1,<3.0.0)
Requires-Dist: toml (>=0.10.2,<0.11.0)
Requires-Dist: tqdm (>=4.56.0,<5.0.0)
Requires-Dist: typer[all] (>=0.3.2,<0.4.0)
Project-URL: Bug Tracker, https://github.com/solider245/cit/issues
Project-URL: Documentation, https://github.com/solider245/cit.git
Project-URL: Repository, https://github.com/solider245/cit.git
